dfchain/__init__.py
dfchain/api/__init__.py
dfchain/api/pipeline.py
dfchain/api/read_csv.py
dfchain/api/task.py
dfchain/backends/__init__.py
dfchain/backends/pandas/__init__.py
dfchain/backends/pandas/executor_impl.py
dfchain/backends/sqlite/__init__.py
dfchain/backends/sqlite/executor_impl.py
dfchain/backends/sqlite/models.py
dfchain/backends/sqlite/schema.py
dfchain/backends/sqlite/util.py
dfchain/backends/sqlite/adapters/__init__.py
dfchain/backends/sqlite/adapters/csvreader.py
dfchain/core/__init__.py
dfchain/core/_api/__init__.py
dfchain/core/_api/read_csv.py
dfchain/core/_api/to_csv.py
dfchain/core/executor/__init__.py
dfchain/core/executor/_abc.py
dfchain/core/executor/groupbylike.py
dfchain/core/executor/partitionable.py
dfchain-0.1.2.dist-info/METADATA
dfchain-0.1.2.dist-info/WHEEL
dfchain-0.1.2.dist-info/top_level.txt
dfchain-0.1.2.dist-info/RECORD
