Metadata-Version: 2.4
Name: dfchain
Version: 0.1.2
Summary: Lightweight library to stream Pandas workflows
Author-email: Alexander Wei <alexander-wei@users.noreply.github.com>
License: MIT
Project-URL: Homepage, https://alexander-wei.github.io/dfchain/
Project-URL: Repository, https://github.com/alexander-wei/dfchain
Project-URL: Documentation, https://alexander-wei.github.io/dfchain/
Project-URL: Bug Tracker, https://github.com/alexander-wei/dfchain/issues
Keywords: pandas,etl,dataframe,pipeline,sqlite
Classifier: Development Status :: 2 - Pre-Alpha
Classifier: Intended Audience :: Developers
Classifier: License :: OSI Approved :: MIT License
Classifier: Programming Language :: Python :: 3
Classifier: Programming Language :: Python :: 3.13
Classifier: Programming Language :: Python :: 3.14
Classifier: Topic :: Software Development :: Libraries
Requires-Python: >=3.12
Requires-Dist: pandas>=2
Requires-Dist: SQLAlchemy>=2
